monitoring_system_report6/__init__.py
monitoring_system_report6/ruuuuuun.py
monitoring_system_report6/agent/__init__.py
monitoring_system_report6/agent/agent.py
monitoring_system_report6/agent/metrics_utils.py
monitoring_system_report6/server/__init__.py
monitoring_system_report6/server/config.conf
monitoring_system_report6/server/config_loader.py
monitoring_system_report6/server/http_bridge.py
monitoring_system_report6/server/server.py
monitoring_system_report6/server/templates/dashboard.html
final_test_srver_report002-0.1.dist-info/METADATA
final_test_srver_report002-0.1.dist-info/WHEEL
final_test_srver_report002-0.1.dist-info/entry_points.txt
final_test_srver_report002-0.1.dist-info/top_level.txt
final_test_srver_report002-0.1.dist-info/RECORD
