Metadata-Version: 2.1
Name: final-test-srver-report002
Version: 0.1
Summary: A monitoring system with an agent and a server.
Home-page: UNKNOWN
Author: Your Name
Author-email: your.email@example.com
License: UNKNOWN
Platform: UNKNOWN
Classifier: Programming Language :: Python :: 3
Classifier: License :: OSI Approved :: MIT License
Classifier: Operating System :: OS Independent
Requires-Python: >=3.6
Requires-Dist: flask
Requires-Dist: psutil
